Metadata-Version: 1.0
Name: probabfunc
Version: 0.2
Summary: Gaussian and Binomial/Normal distributions
Home-page: UNKNOWN
Author: Dhiraj Kumar Chaudhary
Author-email: dhirajc963@gmail.com
License: UNKNOWN
Platform: UNKNOWN
